{
    "content": [
        {
            "zuluAccountId": 2217991,
            "brokerAccountId": 2075293,
            "name": "TIKM2075293F",
            "publicAccount": true,
            "publicPage": "follower/2075293",
            "brokerId": 226,
            "brokerName": "Tickmill EU",
            "countryCode": "CZ",
            "countryNameResourceId": "czechrepublic",
            "profitPips": 51.8,
            "profitUsd": 5.0,
            "profitSharing": true,
            "profileName": "TIKM2075293F"
        },
        {
            "zuluAccountId": 917620,
            "brokerAccountId": 945365,
            "name": "AAA945365F",
            "publicAccount": true,
            "publicPage": "follower/945365",
            "brokerId": 41,
            "brokerName": "AAAFX",
            "countryCode": "CZ",
            "countryNameResourceId": "czechrepublic",
            "profitPips": 0.0,
            "profitUsd": 0.0,
            "profitSharing": false,
            "profileName": "AAA945365F"
        },
        {
            "zuluAccountId": 2296759,
            "brokerAccountId": 2119259,
            "name": "AAA2119259F",
            "publicAccount": true,
            "publicPage": "follower/2119259",
            "brokerId": 41,
            "brokerName": "AAAFX",
            "countryCode": "IT",
            "countryNameResourceId": "italy",
            "profitPips": 0.0,
            "profitUsd": 0.0,
            "profitSharing": true,
            "profileName": "AAA2119259F"
        },
        {
            "zuluAccountId": 2258129,
            "brokerAccountId": 2097261,
            "name": "TIKM2097261F",
            "publicAccount": true,
            "publicPage": "follower/2097261",
            "brokerId": 226,
            "brokerName": "Tickmill EU",
            "countryCode": "ES",
            "countryNameResourceId": "spain",
            "profitPips": 0.0,
            "profitUsd": 0.0,
            "profitSharing": true,
            "profileName": "TIKM2097261F"
        },
        {
            "zuluAccountId": 2251534,
            "brokerAccountId": 2093000,
            "name": "WELT2093000F",
            "publicAccount": true,
            "publicPage": "follower/2093000",
            "brokerId": 61,
            "brokerName": "Weltrade",
            "countryCode": "TH",
            "countryNameResourceId": "thailand",
            "profitPips": 0.0,
            "profitUsd": 0.0,
            "profitSharing": false,
            "profileName": "WELT2093000F"
        },
        {
            "zuluAccountId": 1509603,
            "brokerAccountId": 1523918,
            "name": "AAA1523918F",
            "publicAccount": true,
            "publicPage": "follower/1523918",
            "brokerId": 41,
            "brokerName": "AAAFX",
            "countryCode": "NL",
            "countryNameResourceId": "netherlands",
            "profitPips": 41.2,
            "profitUsd": -58.0,
            "profitSharing": false,
            "profileName": "AAA1523918F"
        }
    ],
    "last": true,
    "totalElements": 6,
    "totalPages": 1,
    "numberOfElements": 6,
    "size": 1800,
    "number": 0,
    "first": true
}